TripletVoting-1.2.data/scripts/tripVote_complete_trees.py
tripVote/__init__.py
tripVote/placement_lib.py
tripVote/tripvote_lib.py
tripVote/utils.py
TripletVoting-1.2.dist-info/COPYING
TripletVoting-1.2.dist-info/COPYING.LESSER
TripletVoting-1.2.dist-info/LICENSE
TripletVoting-1.2.dist-info/METADATA
TripletVoting-1.2.dist-info/WHEEL
TripletVoting-1.2.dist-info/top_level.txt
TripletVoting-1.2.dist-info/RECORD
