Metadata-Version: 2.1
Name: TripletVoting
Version: 1.2
Summary: The tripvote Python software
Home-page: https://github.com/uym2/tripVote
Author: uym2
Author-email: ceciliamaitouyen@gmail.com
License: UNKNOWN
Platform: UNKNOWN
Classifier: Environment :: Console
Classifier: Intended Audience :: Developers
Classifier: Intended Audience :: Science/Research
Classifier: License :: OSI Approved :: GNU General Public License (GPL)
Classifier: Natural Language :: English
Classifier: Programming Language :: Python
Classifier: Topic :: Scientific/Engineering :: Bio-Informatics
Requires-Python: >=3
License-File: LICENSE
License-File: COPYING
License-File: COPYING.LESSER
Requires-Dist: tqdist
Requires-Dist: treeswift
Requires-Dist: triproot
Requires-Dist: setuptools
Requires-Dist: wheel
